marinholab/papers/tro2022/adaptive_control/__init__.py
marinholab/papers/tro2022/adaptive_control/_core.cpython-312-darwin.so
marinholab/papers/tro2022/adaptive_control/Example_ParameterSpaceEDH/__init__.py
marinholab_papers_tro2022_adaptivecontrol-25.6.0.33.dist-info/METADATA
marinholab_papers_tro2022_adaptivecontrol-25.6.0.33.dist-info/WHEEL
marinholab_papers_tro2022_adaptivecontrol-25.6.0.33.dist-info/top_level.txt
marinholab_papers_tro2022_adaptivecontrol-25.6.0.33.dist-info/RECORD
