Metadata-Version: 2.4
Name: marinholab-papers-tro2022-adaptivecontrol
Version: 25.6.0.33
Summary: A Python implementation of an example of 'Adaptive Constrained Kinematic Control using Partial or Complete Task-Space Measurements'
Author-email: "Murilo M. Marinho" <murilomarinho@ieee.org>
Maintainer-email: "Murilo M. Marinho" <murilomarinho@ieee.org>
Requires-Python: >=3.9
Requires-Dist: dqrobotics>=23.4.0a49
Requires-Dist: dqrobotics-interface-coppeliasim-zmq
